public class ListNode {
    public int value;
    public ListNode next;

    public ListNode() {
    }

    public ListNode(int value) {
        this.value = value;
    }

    public ListNode(int value, ListNode next) {
        this.value = value;
        this.next = next;
    }
}

源代码 > 编译 > 反编译: 查看代码编译后的字节码指令
> javap -c C:\Users\tchen\Desktop\test\ListNode.class

  Compiled from "ListNode.java"
  public class algorithms.datamodel.ListNode {
     public int value;
     public algorithms.datamodel.ListNode next;

     public algorithms.datamodel.ListNode();
       Code:
          0: aload_0
          1: invokespecial #1                  // Method java/lang/Object."<init>":()V
          4: return

     public algorithms.datamodel.ListNode(int);
       Code:
          0: aload_0
          1: invokespecial #1                  // Method java/lang/Object."<init>":()V
          4: aload_0
          5: iload_1
          6: putfield      #7                  // Field value:I
          9: return

     public algorithms.datamodel.ListNode(int, algorithms.datamodel.ListNode);
       Code:
          0: aload_0
          1: invokespecial #1                  // Method java/lang/Object."<init>":()V
          4: aload_0
          5: iload_1
          6: putfield      #7                  // Field value:I
          9: aload_0
         10: aload_2
         11: putfield      #13                 // Field next:Lalgorithms/datamodel/ListNode;
         14: return
  }